tests/__init__.py
tradebest_ctp/__init__.py
tradebest_ctp/6.7.7_20240607/version.txt
tradebest_ctp/6.7.7_20240607/linux64/_thostmduserapi.so
tradebest_ctp/6.7.7_20240607/linux64/_thosttraderapi.so
tradebest_ctp/6.7.7_20240607/linux64/libthostmduserapi_se.so
tradebest_ctp/6.7.7_20240607/linux64/libthosttraderapi_se.so
tradebest_ctp/6.7.7_20240607/linux64/thostmduserapi.py
tradebest_ctp/6.7.7_20240607/linux64/thosttraderapi.py
tradebest_ctp/6.7.7_20240607/win32/thostmduserapi.py
tradebest_ctp/6.7.7_20240607/win32/thostmduserapi_se.dll
tradebest_ctp/6.7.7_20240607/win32/thosttraderapi.py
tradebest_ctp/6.7.7_20240607/win32/thosttraderapi_se.dll
tradebest_ctp/6.7.7_20240607/win64/thostmduserapi.py
tradebest_ctp/6.7.7_20240607/win64/thostmduserapi_se.dll
tradebest_ctp/6.7.7_20240607/win64/thosttraderapi.py
tradebest_ctp/6.7.7_20240607/win64/thosttraderapi_se.dll
tradebest_ctp/mdapi/__init__.py
tradebest_ctp/tdapi/__init__.py
tradebest_ctp_python-6.7.8.dist-info/licenses/LICENSE
tradebest_ctp_python-6.7.8.dist-info/METADATA
tradebest_ctp_python-6.7.8.dist-info/WHEEL
tradebest_ctp_python-6.7.8.dist-info/top_level.txt
tradebest_ctp_python-6.7.8.dist-info/RECORD
